{
    "update": "2022-08-22",
    "season": 11,
    "90": {
        "id": 90,
        "name": "test0",
        "sur": "TEST",
        "nick": [
            "zero",
            "null",
            "zilch"
        ],
        "attendance": 43,
        "match played": 32,
        "goal": 33,
        "assist": 16,
        "auto goal": 0,
        "winrate": 12.0,
        "goal average": 33.0,
        "assist average": 16.0,
        "auto goal average": 0.0,
        "win": 12,
        "loss": 17,
        "draw": 17,
        "MMR": 1000.0,
        "S8R": 1050,
        "winstreak": 0,
        "last match played": "draw",
        "season 9": {
            "SR": 1039.5943189753834,
            "rank": "Silver",
            "goal": 5,
            "assist": 2,
            "auto goal": 0,
            "attendance": 6,
            "match played": 32,
            "standing": 0,
            "win": 5,
            "loss": 1,
            "draw": 7,
            "winrate": 12.0,
            "goal average": 33.0,
            "assist average": 16.0,
            "auto goal average": 0.0
        },
        "winsrteak": 0,
        "season 10": {
            "SR": 999,
            "rank": "Unranked",
            "goal": 0,
            "assist": 0,
            "auto goal": 0,
            "attendance": 0,
            "standing": 0,
            "win": 0,
            "loss": 0,
            "draw": 0,
            "winrate": 0,
            "goal average": 0,
            "assist average": 0,
            "auto goal average": 0
        },
        "season 11": {
            "SR": 999,
            "rank": "Unranked",
            "goal": 0,
            "assist": 0,
            "auto goal": 0,
            "attendance": 0,
            "standing": 0,
            "win": 0,
            "loss": 0,
            "draw": 0,
            "winrate": 0,
            "goal average": 0,
            "assist average": 0,
            "auto goal average": 0,
            "match played": 0
        }
    },
    "91": {
        "id": 91,
        "name": "test1",
        "sur": "test",
        "nick": [
            "uno",
            "ichi"
        ],
        "attendance": 32,
        "match played": 16,
        "goal": 0,
        "assist": 5,
        "auto goal": 0,
        "winrate": 2.5,
        "goal average": 0.0,
        "assist average": 2.5,
        "win": 5,
        "loss": 0,
        "draw": 16,
        "auto goal average": 0.0,
        "MMR": 1176.776695296637,
        "S8R": 1100,
        "winstreak": 0,
        "last match played": "draw",
        "season 9": {
            "SR": 1203.813806837039,
            "rank": "Platinum",
            "goal": 0,
            "assist": 5,
            "auto goal": 0,
            "attendance": 6,
            "match played": 16,
            "standing": 0,
            "win": 5,
            "loss": 0,
            "draw": 6,
            "winrate": 2.5,
            "goal average": 0.0,
            "assist average": 2.5,
            "auto goal average": 0.0
        },
        "winsrteak": 0,
        "season 10": {
            "SR": 999,
            "rank": "Unranked",
            "goal": 0,
            "assist": 0,
            "auto goal": 0,
            "attendance": 0,
            "standing": 0,
            "win": 0,
            "loss": 0,
            "draw": 0,
            "winrate": 0,
            "goal average": 0,
            "assist average": 0,
            "auto goal average": 0
        },
        "season 11": {
            "SR": 999,
            "rank": "Unranked",
            "goal": 0,
            "assist": 0,
            "auto goal": 0,
            "attendance": 0,
            "standing": 0,
            "win": 0,
            "loss": 0,
            "draw": 0,
            "winrate": 0,
            "goal average": 0,
            "assist average": 0,
            "auto goal average": 0,
            "match played": 0
        }
    },
    "92": {
        "id": 92,
        "name": "test2",
        "sur": "TEST",
        "nick": [],
        "attendance": 32,
        "match played": 16,
        "goal": 5,
        "assist": 0,
        "auto goal": 0,
        "winrate": 1.25,
        "goal average": 1.25,
        "assist average": 0.0,
        "win": 5,
        "loss": 0,
        "draw": 16,
        "auto goal average": 0.0,
        "MMR": 1176.776695296637,
        "S8R": 1030,
        "winstreak": 0,
        "last match played": "draw",
        "season 9": {
            "SR": 1235.813806837039,
            "rank": "Platinum",
            "goal": 5,
            "assist": 0,
            "auto goal": 0,
            "attendance": 6,
            "match played": 16,
            "standing": 0,
            "win": 5,
            "loss": 0,
            "draw": 6,
            "winrate": 1.25,
            "goal average": 1.25,
            "assist average": 0.0,
            "auto goal average": 0.0
        },
        "winsrteak": 0,
        "season 10": {
            "SR": 999,
            "rank": "Unranked",
            "goal": 0,
            "assist": 0,
            "auto goal": 0,
            "attendance": 0,
            "standing": 0,
            "win": 0,
            "loss": 0,
            "draw": 0,
            "winrate": 0,
            "goal average": 0,
            "assist average": 0,
            "auto goal average": 0
        },
        "season 11": {
            "SR": 999,
            "rank": "Unranked",
            "goal": 0,
            "assist": 0,
            "auto goal": 0,
            "attendance": 0,
            "standing": 0,
            "win": 0,
            "loss": 0,
            "draw": 0,
            "winrate": 0,
            "goal average": 0,
            "assist average": 0,
            "auto goal average": 0,
            "match played": 0
        }
    },
    "93": {
        "id": 93,
        "name": "test3",
        "sur": "TEST",
        "nick": [],
        "attendance": 32,
        "match played": 16,
        "goal": 5,
        "assist": 0,
        "auto goal": 0,
        "winrate": 0.8333333333333334,
        "goal average": 0.8333333333333334,
        "assist average": 0.0,
        "win": 5,
        "loss": 5,
        "draw": 11,
        "auto goal average": 0.0,
        "MMR": 1176.7738219631735,
        "S8R": 1000,
        "winstreak": 0,
        "last match played": "draw",
        "season 9": {
            "SR": 1102.4056810246163,
            "rank": "Gold",
            "goal": 5,
            "assist": 0,
            "auto goal": 0,
            "attendance": 6,
            "match played": 16,
            "standing": 0,
            "win": 5,
            "loss": 5,
            "draw": 1,
            "winrate": 0.8333333333333334,
            "goal average": 0.8333333333333334,
            "assist average": 0.0,
            "auto goal average": 0.0
        },
        "winsrteak": 0,
        "season 10": {
            "SR": 999,
            "rank": "Unranked",
            "goal": 0,
            "assist": 0,
            "auto goal": 0,
            "attendance": 0,
            "standing": 0,
            "win": 0,
            "loss": 0,
            "draw": 0,
            "winrate": 0,
            "goal average": 0,
            "assist average": 0,
            "auto goal average": 0
        },
        "season 11": {
            "SR": 999,
            "rank": "Unranked",
            "goal": 0,
            "assist": 0,
            "auto goal": 0,
            "attendance": 0,
            "standing": 0,
            "win": 0,
            "loss": 0,
            "draw": 0,
            "winrate": 0,
            "goal average": 0,
            "assist average": 0,
            "auto goal average": 0,
            "match played": 0
        }
    },
    "94": {
        "id": 94,
        "name": "test4",
        "sur": "TEST",
        "nick": [],
        "attendance": 32,
        "match played": 16,
        "goal": 15,
        "assist": 0,
        "auto goal": 0,
        "winrate": 0.625,
        "goal average": 1.875,
        "assist average": 0.0,
        "win": 5,
        "loss": 5,
        "draw": 11,
        "auto goal average": 0.0,
        "MMR": 1176.7766952957516,
        "S8R": 1000,
        "winstreak": 0,
        "last match played": "draw",
        "season 9": {
            "SR": 1032.405681024616,
            "rank": "Silver",
            "goal": 1,
            "assist": 0,
            "auto goal": 0,
            "attendance": 6,
            "match played": 16,
            "standing": 0,
            "win": 5,
            "loss": 5,
            "draw": 1,
            "winrate": 0.625,
            "goal average": 1.875,
            "assist average": 0.0,
            "auto goal average": 0.0
        },
        "winsrteak": 0,
        "season 10": {
            "SR": 999,
            "rank": "Unranked",
            "goal": 0,
            "assist": 0,
            "auto goal": 0,
            "attendance": 0,
            "standing": 0,
            "win": 0,
            "loss": 0,
            "draw": 0,
            "winrate": 0,
            "goal average": 0,
            "assist average": 0,
            "auto goal average": 0
        },
        "season 11": {
            "SR": 999,
            "rank": "Unranked",
            "goal": 0,
            "assist": 0,
            "auto goal": 0,
            "attendance": 0,
            "standing": 0,
            "win": 0,
            "loss": 0,
            "draw": 0,
            "winrate": 0,
            "goal average": 0,
            "assist average": 0,
            "auto goal average": 0,
            "match played": 0
        }
    },
    "95": {
        "id": 95,
        "name": "test5",
        "sur": "TEST",
        "nick": [],
        "attendance": 32,
        "match played": 16,
        "goal": 5,
        "assist": 0,
        "auto goal": 0,
        "winrate": 0.5,
        "goal average": 0.5,
        "assist average": 0.0,
        "win": 5,
        "loss": 5,
        "draw": 11,
        "auto goal average": 0.0,
        "MMR": 1074.8887334121841,
        "S8R": 1020,
        "winstreak": 0,
        "last match played": "draw",
        "season 9": {
            "SR": 1102.4056810246163,
            "rank": "Gold",
            "goal": 5,
            "assist": 0,
            "auto goal": 0,
            "attendance": 6,
            "match played": 16,
            "standing": 0,
            "win": 5,
            "loss": 5,
            "draw": 1,
            "winrate": 0.5,
            "goal average": 0.5,
            "assist average": 0.0,
            "auto goal average": 0.0
        },
        "winsrteak": 0,
        "season 10": {
            "SR": 999,
            "rank": "Unranked",
            "goal": 0,
            "assist": 0,
            "auto goal": 0,
            "attendance": 0,
            "standing": 0,
            "win": 0,
            "loss": 0,
            "draw": 0,
            "winrate": 0,
            "goal average": 0,
            "assist average": 0,
            "auto goal average": 0
        },
        "season 11": {
            "SR": 999,
            "rank": "Unranked",
            "goal": 0,
            "assist": 0,
            "auto goal": 0,
            "attendance": 0,
            "standing": 0,
            "win": 0,
            "loss": 0,
            "draw": 0,
            "winrate": 0,
            "goal average": 0,
            "assist average": 0,
            "auto goal average": 0,
            "match played": 0
        }
    },
    "96": {
        "id": 96,
        "name": "test6",
        "sur": "TEST",
        "nick": [],
        "attendance": 32,
        "match played": 16,
        "goal": 25,
        "assist": 15,
        "auto goal": 0,
        "winrate": 0.0,
        "goal average": 2.0833333333333335,
        "assist average": 1.25,
        "win": 0,
        "loss": 5,
        "draw": 16,
        "auto goal average": 0.0,
        "MMR": 1166.1207786049501,
        "S8R": 1000,
        "winstreak": 0,
        "last match played": "draw",
        "season 9": {
            "SR": 994.7805121383444,
            "rank": "Bronze",
            "goal": 11,
            "assist": 1,
            "auto goal": 0,
            "attendance": 6,
            "match played": 16,
            "standing": 0,
            "win": 0,
            "loss": 5,
            "draw": 6,
            "winrate": 0.0,
            "goal average": 2.0833333333333335,
            "assist average": 1.25,
            "auto goal average": 0.0
        },
        "winsrteak": 0,
        "season 10": {
            "SR": 999,
            "rank": "Unranked",
            "goal": 0,
            "assist": 0,
            "auto goal": 0,
            "attendance": 0,
            "standing": 0,
            "win": 0,
            "loss": 0,
            "draw": 0,
            "winrate": 0,
            "goal average": 0,
            "assist average": 0,
            "auto goal average": 0
        },
        "season 11": {
            "SR": 999,
            "rank": "Unranked",
            "goal": 0,
            "assist": 0,
            "auto goal": 0,
            "attendance": 0,
            "standing": 0,
            "win": 0,
            "loss": 0,
            "draw": 0,
            "winrate": 0,
            "goal average": 0,
            "assist average": 0,
            "auto goal average": 0,
            "match played": 0
        }
    },
    "97": {
        "id": 90,
        "name": "test7",
        "sur": "TEST",
        "nick": [],
        "attendance": 42,
        "match played": 0,
        "goal": 33,
        "assist": 15,
        "auto goal": 0,
        "winrate": 0.18421052631578946,
        "goal average": 0.7631578947368421,
        "assist average": 0.39473684210526316,
        "auto goal average": 0.0,
        "win": 11,
        "loss": 16,
        "draw": 15,
        "MMR": 1025.6768538394247,
        "S8R": 1050,
        "winstreak": 0,
        "last match played": "draw",
        "season 9": {
            "SR": 1015.0,
            "rank": "Silver",
            "goal": 5,
            "assist": 1,
            "auto goal": 0,
            "attendance": 5,
            "match played": 0,
            "standing": 0,
            "win": 4,
            "loss": 0,
            "draw": 5,
            "winrate": 0.18421052631578946,
            "goal average": 0.7631578947368421,
            "assist average": 0.39473684210526316,
            "auto goal average": 0.0
        },
        "winsrteak": 0,
        "season 10": {
            "SR": 999,
            "rank": "Unranked",
            "goal": 0,
            "assist": 0,
            "auto goal": 0,
            "attendance": 0,
            "standing": 0,
            "win": 0,
            "loss": 0,
            "draw": 0,
            "winrate": 0,
            "goal average": 0,
            "assist average": 0,
            "auto goal average": 0
        },
        "season 11": {
            "SR": 999,
            "rank": "Unranked",
            "goal": 0,
            "assist": 0,
            "auto goal": 0,
            "attendance": 0,
            "standing": 0,
            "win": 0,
            "loss": 0,
            "draw": 0,
            "winrate": 0,
            "goal average": 0,
            "assist average": 0,
            "auto goal average": 0,
            "match played": 0
        }
    },
    "98": {
        "id": 90,
        "name": "test8",
        "sur": "TEST",
        "nick": [],
        "attendance": 42,
        "match played": 0,
        "goal": 33,
        "assist": 15,
        "auto goal": 0,
        "winrate": 0.18421052631578946,
        "goal average": 0.7631578947368421,
        "assist average": 0.39473684210526316,
        "auto goal average": 0.0,
        "win": 11,
        "loss": 16,
        "draw": 15,
        "MMR": 1025.6768538394247,
        "S8R": 1050,
        "winstreak": 0,
        "last match played": "draw",
        "season 9": {
            "SR": 1015.0,
            "rank": "Silver",
            "goal": 5,
            "assist": 1,
            "auto goal": 0,
            "attendance": 5,
            "match played": 0,
            "standing": 0,
            "win": 4,
            "loss": 0,
            "draw": 5,
            "winrate": 0.18421052631578946,
            "goal average": 0.7631578947368421,
            "assist average": 0.39473684210526316,
            "auto goal average": 0.0
        },
        "winsrteak": 0,
        "season 10": {
            "SR": 999,
            "rank": "Unranked",
            "goal": 0,
            "assist": 0,
            "auto goal": 0,
            "attendance": 0,
            "standing": 0,
            "win": 0,
            "loss": 0,
            "draw": 0,
            "winrate": 0,
            "goal average": 0,
            "assist average": 0,
            "auto goal average": 0
        },
        "season 11": {
            "SR": 999,
            "rank": "Unranked",
            "goal": 0,
            "assist": 0,
            "auto goal": 0,
            "attendance": 0,
            "standing": 0,
            "win": 0,
            "loss": 0,
            "draw": 0,
            "winrate": 0,
            "goal average": 0,
            "assist average": 0,
            "auto goal average": 0,
            "match played": 0
        }
    },
    "99": {
        "id": 99,
        "name": "test9",
        "sur": "TEST",
        "nick": [],
        "attendance": 27,
        "match played": 0,
        "goal": 15,
        "assist": 0,
        "auto goal": 0,
        "winrate": 0.0,
        "goal average": 0.5555555555555556,
        "assist average": 0.0,
        "win": 0,
        "loss": 0,
        "draw": 11,
        "auto goal average": 0.0,
        "MMR": 1000.4691743118076,
        "S8R": 1000,
        "winstreak": 0,
        "last match played": "draw",
        "season 9": {
            "SR": 1009.0,
            "rank": "Silver",
            "goal": 1,
            "assist": 0,
            "auto goal": 0,
            "attendance": 1,
            "match played": 0,
            "standing": 0,
            "win": 0,
            "loss": 0,
            "draw": 1,
            "winrate": 0.0,
            "goal average": 0.5555555555555556,
            "assist average": 0.0,
            "auto goal average": 0.0
        },
        "winsrteak": 0,
        "season 10": {
            "SR": 999,
            "rank": "Unranked",
            "goal": 0,
            "assist": 0,
            "auto goal": 0,
            "attendance": 0,
            "standing": 0,
            "win": 0,
            "loss": 0,
            "draw": 0,
            "winrate": 0,
            "goal average": 0,
            "assist average": 0,
            "auto goal average": 0
        },
        "season 11": {
            "SR": 999,
            "rank": "Unranked",
            "goal": 0,
            "assist": 0,
            "auto goal": 0,
            "attendance": 0,
            "standing": 0,
            "win": 0,
            "loss": 0,
            "draw": 0,
            "winrate": 0,
            "goal average": 0,
            "assist average": 0,
            "auto goal average": 0,
            "match played": 0
        }
    }
}